KlAkOAPI/AKPatches.py
KlAkOAPI/AdHosts.py
KlAkOAPI/AdSecManager.py
KlAkOAPI/AdfsSso.py
KlAkOAPI/AdmServer.py
KlAkOAPI/AdmServerSettings.py
KlAkOAPI/AppCtrlApi.py
KlAkOAPI/AsyncActionStateChecker.py
KlAkOAPI/Base.py
KlAkOAPI/CertPoolCtrl.py
KlAkOAPI/CertPoolCtrl2.py
KlAkOAPI/CgwHelper.py
KlAkOAPI/ChunkAccessor.py
KlAkOAPI/CloudAccess.py
KlAkOAPI/ConEvents.py
KlAkOAPI/ConnectionHelper.py
KlAkOAPI/DataProtectionApi.py
KlAkOAPI/DatabaseInfo.py
KlAkOAPI/DpeKeyService.py
KlAkOAPI/Error.py
KlAkOAPI/EventNotificationProperties.py
KlAkOAPI/EventNotificationsApi.py
KlAkOAPI/EventProcessing.py
KlAkOAPI/EventProcessingFactory.py
KlAkOAPI/ExtAud.py
KlAkOAPI/FileCategorizer2.py
KlAkOAPI/FilesAcceptor.py
KlAkOAPI/GatewayConnection.py
KlAkOAPI/GroupSync.py
KlAkOAPI/GroupSyncIterator.py
KlAkOAPI/GroupTaskControlApi.py
KlAkOAPI/HWInvStorage.py
KlAkOAPI/HostGroup.py
KlAkOAPI/HostMoveRules.py
KlAkOAPI/HostTagsApi.py
KlAkOAPI/HostTagsRulesApi.py
KlAkOAPI/HostTasks.py
KlAkOAPI/HstAccessControl.py
KlAkOAPI/IWebSrvSettings.py
KlAkOAPI/IWebUsersSrv.py
KlAkOAPI/InvLicenseProducts.py
KlAkOAPI/InventoryApi.py
KlAkOAPI/KLEVerControl.py
KlAkOAPI/KLEVerTestApi.py
KlAkOAPI/KeyService.py
KlAkOAPI/KillChain.py
KlAkOAPI/KsnInternal.py
KlAkOAPI/LicenseInfoSync.py
KlAkOAPI/LicenseKeys.py
KlAkOAPI/LicensePolicy.py
KlAkOAPI/Limits.py
KlAkOAPI/ListTags.py
KlAkOAPI/MigrationData.py
KlAkOAPI/Multitenancy.py
KlAkOAPI/NagCgwHelper.py
KlAkOAPI/NagGuiCalls.py
KlAkOAPI/NagHstCtl.py
KlAkOAPI/NagNetworkListApi.py
KlAkOAPI/NagRdu.py
KlAkOAPI/NagRemoteScreen.py
KlAkOAPI/NlaDefinedNetworks.py
KlAkOAPI/OsVersion.py
KlAkOAPI/PLCDevApi.py
KlAkOAPI/PackagesApi.py
KlAkOAPI/Params.py
KlAkOAPI/PatchParameters.py
KlAkOAPI/PluginData.py
KlAkOAPI/Policy.py
KlAkOAPI/PolicyProfiles.py
KlAkOAPI/QBTNetworkListApi.py
KlAkOAPI/QueriesStorage.py
KlAkOAPI/ReportManager.py
KlAkOAPI/RetrFiles.py
KlAkOAPI/RetrFiles2.py
KlAkOAPI/ScanDiapasons.py
KlAkOAPI/SeamlessUpdatesTestApi.py
KlAkOAPI/SecurityPolicy.py
KlAkOAPI/SecurityPolicy3.py
ussl_ksc-1.0.0.dist-info/METADATA
ussl_ksc-1.0.0.dist-info/WHEEL
ussl_ksc-1.0.0.dist-info/RECORD
